{
    "furina" : {
        "name" : "Furina",
        "element" : "Hydro",
        "bestweapon" : "Splendor of Tranquil Waters",
        "f2p" : "Favonious Sword",
        "artifact" : "Gold",
        "team" : "Neuvallete, Escoffier, Mona",
        "hp" : "40000",
        "critdmg" : "180%",
        "critrt" : "70%"
    },
    "chasca" : {
        "name" : "Chasca",
        "element" : "Anemo",
        "bestweapon" : "Astral Vulture's Crimson Plumage",
        "f2p" : "Chain Breaker",
        "artifact" : "Obsidian codex",
        "team" : "Ororon, Furina, Bennet",
        "atk" : "2000",
        "critdmg" : "200%",
        "critrt" : "60%"
        
    },
    "zibai" : {
        "name" : "Zibai",
        "element" : "Geo",
        "bestweapon" : "Lightbearing Moonshard",
        "f2p" : "Flute of Ezpitzal",
        "artifact" : "Night of the Sky's Unveiling",
        "team" : "Linnea, Columbina, Illuga/Gorou",
        "def" : "2000",
        "critdmg" : "220%",
        "critrt" : "70%"
    }


}